odoo/addons/account_check_printing_report_base/README.rst
odoo/addons/account_check_printing_report_base/__init__.py
odoo/addons/account_check_printing_report_base/__manifest__.py
odoo/addons/account_check_printing_report_base/data/account_payment_check_report_data.xml
odoo/addons/account_check_printing_report_base/data/report_paperformat.xml
odoo/addons/account_check_printing_report_base/i18n/account_check_printing_report_base.pot
odoo/addons/account_check_printing_report_base/i18n/es.po
odoo/addons/account_check_printing_report_base/i18n/pt.po
odoo/addons/account_check_printing_report_base/models/__init__.py
odoo/addons/account_check_printing_report_base/models/account_journal.py
odoo/addons/account_check_printing_report_base/models/account_payment.py
odoo/addons/account_check_printing_report_base/models/account_payment_check_report.py
odoo/addons/account_check_printing_report_base/models/res_company.py
odoo/addons/account_check_printing_report_base/readme/CONFIGURE.rst
odoo/addons/account_check_printing_report_base/readme/CONTRIBUTORS.rst
odoo/addons/account_check_printing_report_base/readme/DESCRIPTION.rst
odoo/addons/account_check_printing_report_base/readme/ROADMAP.rst
odoo/addons/account_check_printing_report_base/readme/USAGE.rst
odoo/addons/account_check_printing_report_base/report/__init__.py
odoo/addons/account_check_printing_report_base/report/account_check_writing_report.xml
odoo/addons/account_check_printing_report_base/report/check_print.py
odoo/addons/account_check_printing_report_base/report/lang.py
odoo/addons/account_check_printing_report_base/security/ir.model.access.csv
odoo/addons/account_check_printing_report_base/static/description/icon.png
odoo/addons/account_check_printing_report_base/static/description/index.html
odoo/addons/account_check_printing_report_base/tests/__init__.py
odoo/addons/account_check_printing_report_base/tests/test_check_printing_report.py
odoo13_addon_account_check_printing_report_base-13.0.2.1.2.dist-info/METADATA
odoo13_addon_account_check_printing_report_base-13.0.2.1.2.dist-info/WHEEL
odoo13_addon_account_check_printing_report_base-13.0.2.1.2.dist-info/top_level.txt
odoo13_addon_account_check_printing_report_base-13.0.2.1.2.dist-info/RECORD
