Metadata-Version: 2.1
Name: odoo13-addon-account-check-printing-report-base
Version: 13.0.2.1.2
Summary: Account Check Printing Report Base
Home-page: https://github.com/OCA/account-payment
Author: Eficent,Serpent Consulting Services Pvt. Ltd.,Ursa Information Systems,Odoo Community Association (OCA)
Author-email: support@odoo-community.org
License: AGPL-3
Platform: UNKNOWN
Classifier: Programming Language :: Python
Classifier: Framework :: Odoo
Classifier: License :: OSI Approved :: GNU Affero General Public License v3
Requires-Python: >=3.5
Requires-Dist: num2words
Requires-Dist: odoo13-addon-report-wkhtmltopdf-param
Requires-Dist: odoo (<13.1dev,>=13.0a)
